{"nSwitches": 13, "nHosts": 12, "nTargets": 1, "links": [{"node": "s1", "neighbors": ["s2", "s3", "s4", "s5", "s6", "s7", "s8", "s9", "s10", "s11", "s12", "s13", "h1"]}, {"node": "s2", "neighbors": ["s1", "s3", "s4", "s5", "s6", "s7", "s8", "s9", "s10", "s11", "s12", "s13", "h2"]}, {"node": "s3", "neighbors": ["s1", "s2", "s4", "s5", "s6", "s7", "s8", "s9", "s10", "s11", "s12", "s13", "h3"]}, {"node": "s4", "neighbors": ["s1", "s2", "s3", "s5", "s6", "s7", "s8", "s9", "s10", "s11", "s12", "s13", "h4"]}, {"node": "s5", "neighbors": ["s1", "s2", "s3", "s4", "s6", "s7", "s8", "s9", "s10", "s11", "s12", "s13", "h5"]}, {"node": "s6", "neighbors": ["s1", "s2", "s3", "s4", "s5", "s7", "s8", "s9", "s10", "s11", "s12", "s13", "h6"]}, {"node": "s7", "neighbors": ["s1", "s2", "s3", "s4", "s5", "s6", "s8", "s9", "s10", "s11", "s12", "s13", "h7"]}, {"node": "s8", "neighbors": ["s1", "s2", "s3", "s4", "s5", "s6", "s7", "s9", "s10", "s11", "s12", "s13", "h8"]}, {"node": "s9", "neighbors": ["s1", "s2", "s3", "s4", "s5", "s6", "s7", "s8", "s10", "s11", "s12", "s13", "h9"]}, {"node": "s10", "neighbors": ["s1", "s2", "s3", "s4", "s5", "s6", "s7", "s8", "s9", "s11", "s12", "s13", "h10"]}, {"node": "s11", "neighbors": ["s1", "s2", "s3", "s4", "s5", "s6", "s7", "s8", "s9", "s10", "s12", "s13", "h11"]}, {"node": "s12", "neighbors": ["s1", "s2", "s3", "s4", "s5", "s6", "s7", "s8", "s9", "s10", "s11", "s13", "h12"]}, {"node": "s13", "neighbors": ["s1", "s2", "s3", "s4", "s5", "s6", "s7", "s8", "s9", "s10", "s11", "s12", "t1"]}], "delay": "10ms", "bandwidth": 10}